{
  "main": {
    "id": "fbf80f44a8261b0f",
    "type": "split",
    "children": [
      {
        "id": "c38f1694a1f94346",
        "type": "tabs",
        "children": [
          {
            "id": "ef89970a009731fe",
            "type": "leaf",
            "state": {
              "type": "markdown",
              "state": {
                "file": "Testing/Playwright Testing.md",
                "mode": "source",
                "source": false
              }
            }
          }
        ],
        "stacked": true
      }
    ],
    "direction": "vertical"
  },
  "left": {
    "id": "5028c12129ff13a7",
    "type": "split",
    "children": [
      {
        "id": "355cd293d8c23ef3",
        "type": "tabs",
        "children": [
          {
            "id": "b81c46e29ae6813b",
            "type": "leaf",
            "state": {
              "type": "file-explorer",
              "state": {
                "sortOrder": "alphabetical"
              }
            }
          },
          {
            "id": "32fe32662db9c1f7",
            "type": "leaf",
            "state": {
              "type": "search",
              "state": {
                "query": "",
                "matchingCase": false,
                "explainSearch": false,
                "collapseAll": false,
                "extraContext": false,
                "sortOrder": "alphabetical"
              }
            }
          },
          {
            "id": "c9fef3ae7e93add1",
            "type": "leaf",
            "state": {
              "type": "bookmarks",
              "state": {}
            }
          }
        ]
      }
    ],
    "direction": "horizontal",
    "width": 200
  },
  "right": {
    "id": "08a76d42a085df96",
    "type": "split",
    "children": [
      {
        "id": "9f1cc52388e191ba",
        "type": "tabs",
        "children": [
          {
            "id": "e180bd8f46d1ab57",
            "type": "leaf",
            "state": {
              "type": "backlink",
              "state": {
                "file": "Testing/Playwright Testing.md",
                "collapseAll": false,
                "extraContext": false,
                "sortOrder": "alphabetical",
                "showSearch": false,
                "searchQuery": "",
                "backlinkCollapsed": false,
                "unlinkedCollapsed": true
              }
            }
          },
          {
            "id": "2808e655c4f8e8d8",
            "type": "leaf",
            "state": {
              "type": "outgoing-link",
              "state": {
                "file": "Testing/Playwright Testing.md",
                "linksCollapsed": false,
                "unlinkedCollapsed": true
              }
            }
          },
          {
            "id": "55d31c0f7ba3c95d",
            "type": "leaf",
            "state": {
              "type": "tag",
              "state": {
                "sortOrder": "frequency",
                "useHierarchy": true
              }
            }
          },
          {
            "id": "1e997630ac6e3810",
            "type": "leaf",
            "state": {
              "type": "outline",
              "state": {
                "file": "Testing/Playwright Testing.md"
              }
            }
          }
        ]
      }
    ],
    "direction": "horizontal",
    "width": 300,
    "collapsed": true
  },
  "left-ribbon": {
    "hiddenItems": {
      "switcher:Open quick switcher": false,
      "graph:Open graph view": false,
      "canvas:Create new canvas": false,
      "daily-notes:Open today's daily note": false,
      "templates:Insert template": false,
      "command-palette:Open command palette": false
    }
  },
  "active": "ef89970a009731fe",
  "lastOpenFiles": [
    "Networking/05_IOS (Internetwork Operating System).md",
    "Untitled.md",
    "Networking/02_Addresses of Devices.md",
    "Networking/Topology Discover Protocols/03_OSPF (Open Shortest Path First).md",
    "Networking/Topology Discover Protocols/00_Discovery_protocols.md",
    "Networking/00_Networking.md",
    "Networking/Topology Discover Protocols/01_LLDP (Link Layer Discovery Protocol).md",
    "Networking/Topology Discover Protocols/02_CDP (Cisco Discover Protocol).md",
    "Networking/04_Protocols.md",
    "Networking/Data Collecting Prototcols/04_Trace_Routes.md",
    "Networking/Data Collecting Prototcols/03_WMI(Windows_Manager_Instrumentation)_Protocol.md",
    "Networking/Data Collecting Prototcols/02_SSH(Secure_Shell_Protocol).md",
    "Networking/Data Collecting Prototcols/01_SNMP(Simple_Network_management__Protocol).md",
    "Networking/01_Ping.md",
    "Networking/Data Collecting Prototcols/00_Inventory_Protocols.md",
    "Networking/Data Transfer Protocol/00_Data_Transfer_Protocols.md",
    "Networking/Data Transfer Protocol",
    "Networking/Topology Discover Protocols/01_CDP (Cisco Discover Protocol).md",
    "Networking/Data Collecting Prototcols/04_Inventory_Protocols.md",
    "Networking/Data Collecting Prototcols/02_WMI_Protocol.md",
    "Networking/Data Collecting Prototcols/01_SSH_Protocol.md",
    "Networking/Data Collecting Prototcols/00_SNMP_Protocol.md",
    "Networking/Data Collecting Prototcols/10_Inventory_Protocols.md",
    "Networking/Data Collecting Prototcols/09_Trace_Routes.md",
    "Networking/Data Collecting Prototcols/08_WMI_Protocol.md",
    "Networking/Data Collecting Prototcols/07_SSH_Protocol.md",
    "Networking/Data Collecting Prototcols/06_SNMP_Protocol.md",
    "Networking/Data Collecting Prototcols",
    "Networking/Topology Discover Protocols",
    "Testing",
    "Story",
    "Assests/OSI work flow.png.~tmp",
    "Assests/OSI work flow.png",
    "Assests/protocols of each layers.png",
    "Assests/networking layer.png",
    "Networking",
    "Full Stack/FULL STACK/FULL STACK (MERN) 3be6db690f4b455ebc4a863c6f013341/React fbd6724a183c4cc78e524081942b1e8e/Life Cycle Of a Component React 35d3fd1d97544139a92d82ff01861ddd",
    "Full Stack/FULL STACK/FULL STACK (MERN) 3be6db690f4b455ebc4a863c6f013341/React fbd6724a183c4cc78e524081942b1e8e",
    "Full Stack/FULL STACK/FULL STACK (MERN) 3be6db690f4b455ebc4a863c6f013341",
    "Assests/Django.png",
    "Assests/MVT dijango.png",
    "Assests/lazy route.jpeg",
    "Assests/WhatsApp Image 2024-07-19 at 4.30.37 PM.jpeg",
    "Assests/routing-architecture-angular.png",
    "Assests/jason package lock version.png",
    "Assests/single way and two way.png"
  ]
}